{
	"people": {
		"name": "people",
		"properties": {
			"id": {
				"name": "id",
				"type": "int",
				"primaryKey": true,
				"required": false
			},
			"first_name": {
				"name": "first_name",
				"type": "string",
				"primaryKey": false,
				"required": true
			},
			"last_name": {
				"name": "last_name",
				"type": "string",
				"primaryKey": false,
				"required": true
			},
			"email": {
				"name": "email",
				"type": "string",
				"primaryKey": false,
				"required": true
			}
		}
	},
	"photos": {
		"name": "photos",
		"properties": {
			"id": {
				"name": "id",
				"type": "int",
				"primaryKey": true,
				"required": false
			},
			"person_id": {
				"name": "person_id",
				"type": "int",
				"primaryKey": false,
				"required": true
			},
			"guid": {
				"name": "guid",
				"type": "string",
				"primaryKey": false,
				"required": true
			},
			"date_created": {
				"name": "date_created",
				"type": "date",
				"primaryKey": false,
				"required": true
			}
		}
	}
}